[
  {
    "Type": "BlueprintGeneratedClass",
    "Name": "GCNL_Athena_LlamaRoaster_Firing_C",
    "Properties": {
      "SimpleConstructionScript": {
        "ObjectName": "GCNL_Athena_LlamaRoaster_Firing_C:SimpleConstructionScript_0:SimpleConstructionScript",
        "ObjectPath": "/MotherGameplay/GameplayCues/GCNL_Athena_LlamaRoaster_Firing.5"
      }
    },
    "SuperStruct": {
      "ObjectName": "FortGameplayCueNotify_Loop:Class",
      "ObjectPath": 0
    },
    "Children": [],
    "ChildProperties": [],
    "FuncMap": {},
    "ClassFlags": 8652820,
    "ClassWithin": {
      "ObjectName": "Object:Class",
      "ObjectPath": 0
    },
    "ClassConfigName": "Engine",
    "ClassGeneratedBy": null,
    "Interfaces": [],
    "bCooked": true,
    "ClassDefaultObject": {
      "ObjectName": "Default__GCNL_Athena_LlamaRoaster_Firing_C:GCNL_Athena_LlamaRoaster_Firing_C",
      "ObjectPath": "/MotherGameplay/GameplayCues/GCNL_Athena_LlamaRoaster_Firing.1"
    }
  },
  {
    "Type": "GCNL_Athena_LlamaRoaster_Firing_C",
    "Name": "Default__GCNL_Athena_LlamaRoaster_Firing_C",
    "Properties": {
      "DefaultLoopingAttachment": {
        "SocketName": "Muzzle",
        "bAttachToWeapon": true,
        "bIgnoreScale": false
      },
      "LoopingSounds": [
        {
          "LoopingSoundFadeOutDuration": 0.5,
          "LoopingSoundVolumeLevel": 0.0,
          "Condition": {
            "SourceCondition": "EFortGameplayCueSourceCondition::AnySource",
            "AllowedSurfaces": [],
            "DisallowedSurfaces": [],
            "ChanceToPlay": 1.0,
            "Significance": "EParticleSignificanceLevel::High",
            "RequiredDetailMode": 0,
            "bRequireVisible": false
          },
          "Attachment": {
            "SocketName": null,
            "AttachType": "EFortGameplayCueAttachType::AttachToTarget",
            "bAttachToWeapon": false,
            "bAttachToHitResult": false,
            "bUseUnsmoothedNetworkPosition": false,
            "bIgnoreScale": true,
            "bIgnoreRotation": false,
            "OverrideScale": {
              "X": 1.0,
              "Y": 1.0,
              "Z": 1.0
            },
            "OverrideRotation": {
              "Pitch": 0.0,
              "Yaw": 0.0,
              "Roll": 0.0
            }
          },
          "SoundCue": {
            "ObjectName": "AlienLaser_FireLoop_Close_Cue:SoundCue",
            "ObjectPath": "/MotherGameplay/Sounds/AlienLaser/AlienLaser_FireLoop_Close_Cue.0"
          },
          "DelayBeforePlayInSeconds": 0.0,
          "bOverrideCondition": false,
          "bOverrideAttachment": true
        }
      ],
      "GameplayCueTag": {
        "TagName": "GameplayCue.Athena.LlamaRoaster.Firing"
      },
      "GameplayCueName": "GameplayCue.Athena.LlamaRoaster.Firing",
      "RootComponent": {
        "ObjectName": "Default__GCNL_Athena_LlamaRoaster_Firing_C:RootComponent:SceneComponent",
        "ObjectPath": "/MotherGameplay/GameplayCues/GCNL_Athena_LlamaRoaster_Firing.2"
      }
    }
  },
  {
    "Type": "SceneComponent",
    "Name": "RootComponent",
    "Outer": "Default__GCNL_Athena_LlamaRoaster_Firing_C"
  },
  {
    "Type": "SceneComponent",
    "Name": "DefaultSceneRoot_GEN_VARIABLE",
    "Outer": "GCNL_Athena_LlamaRoaster_Firing_C"
  },
  {
    "Type": "SCS_Node",
    "Name": "SCS_Node_0",
    "Outer": "SimpleConstructionScript_0",
    "Properties": {
      "ComponentClass": {
        "ObjectName": "SceneComponent:Class",
        "ObjectPath": 0
      },
      "ComponentTemplate": {
        "ObjectName": "GCNL_Athena_LlamaRoaster_Firing_C:DefaultSceneRoot_GEN_VARIABLE:SceneComponent",
        "ObjectPath": "/MotherGameplay/GameplayCues/GCNL_Athena_LlamaRoaster_Firing.3"
      },
      "VariableGuid": "1E56FDBE-4B4C9BC7-07DC1CA2-1A8802D2",
      "InternalVariableName": "DefaultSceneRoot"
    }
  },
  {
    "Type": "SimpleConstructionScript",
    "Name": "SimpleConstructionScript_0",
    "Outer": "GCNL_Athena_LlamaRoaster_Firing_C",
    "Properties": {
      "DefaultSceneRootNode": {
        "ObjectName": "SimpleConstructionScript_0:SCS_Node_0:SCS_Node",
        "ObjectPath": "/MotherGameplay/GameplayCues/GCNL_Athena_LlamaRoaster_Firing.4"
      }
    }
  }
]