[
  {
    "Type": "CurveTable",
    "Name": "MotherAttributeData",
    "Rows": {
      "MotherPlaceholder.Defaults.FortHealthSet.MaxHealth": {
        "InterpMode": "ERichCurveInterpMode::RCIM_Linear",
        "Keys": [
          {
            "KeyTime": 0.0,
            "KeyValue": 150.0
          }
        ],
        "DefaultValue": 3.4028235E+38,
        "PreInfinityExtrap": "ERichCurveExtrapolation::RCCE_Constant",
        "PostInfinityExtrap": "ERichCurveExtrapolation::RCCE_Constant"
      },
      "AvacadoEaterDeployed.Defaults.FortHealthSet.MaxHealth": {
        "InterpMode": "ERichCurveInterpMode::RCIM_Linear",
        "Keys": [
          {
            "KeyTime": 0.0,
            "KeyValue": 75.0
          }
        ],
        "DefaultValue": 3.4028235E+38,
        "PreInfinityExtrap": "ERichCurveExtrapolation::RCCE_Constant",
        "PostInfinityExtrap": "ERichCurveExtrapolation::RCCE_Constant"
      },
      "AvacadoEaterBird.Defaults.FortHealthSet.MaxHealth": {
        "InterpMode": "ERichCurveInterpMode::RCIM_Linear",
        "Keys": [
          {
            "KeyTime": 0.0,
            "KeyValue": 60.0
          }
        ],
        "DefaultValue": 3.4028235E+38,
        "PreInfinityExtrap": "ERichCurveExtrapolation::RCCE_Constant",
        "PostInfinityExtrap": "ERichCurveExtrapolation::RCCE_Constant"
      },
      "CageSaddle.Defaults.FortCowVehicleSet.MaxFuel": {
        "InterpMode": "ERichCurveInterpMode::RCIM_Linear",
        "Keys": [
          {
            "KeyTime": 0.0,
            "KeyValue": 100.0
          }
        ],
        "DefaultValue": 3.4028235E+38,
        "PreInfinityExtrap": "ERichCurveExtrapolation::RCCE_Constant",
        "PostInfinityExtrap": "ERichCurveExtrapolation::RCCE_Constant"
      },
      "CageSaddle.Defaults.FortCowVehicleSet.Fuel": {
        "InterpMode": "ERichCurveInterpMode::RCIM_Linear",
        "Keys": [
          {
            "KeyTime": 0.0,
            "KeyValue": 100.0
          }
        ],
        "DefaultValue": 3.4028235E+38,
        "PreInfinityExtrap": "ERichCurveExtrapolation::RCCE_Constant",
        "PostInfinityExtrap": "ERichCurveExtrapolation::RCCE_Constant"
      }
    }
  }
]