[
  {
    "Type": "FortQuestItemDefinition",
    "Name": "quest_s18_transient_BabaYaga_NewBrew_q02",
    "Properties": {
      "QuestType": "EFortQuestType::AthenaTransientQuest",
      "TandemCharacterData": {
        "AssetPathName": "/NPCLibrary/NPCs/BabaYaga/BabaYaga/NPCCharacterData_BabaYaga.NPCCharacterData_BabaYaga",
        "SubPathString": ""
      },
      "bIncludedInCategories": false,
      "bIsShared": true,
      "Rewards": [
        {
          "ItemPrimaryAssetId": {
            "PrimaryAssetType": {
              "Name": "Quest"
            },
            "PrimaryAssetName": "quest_s18_transient_BabaYaga_NewBrew_q03"
          },
          "Quantity": 1
        }
      ],
      "RewardsTable": {
        "ObjectName": "DataTable ChallengeReward_S18_ShardQuest_UC",
        "ObjectPath": "/BattlePassS18/Items/QuestRewards/ChallengeReward_S18_ShardQuest_UC.0"
      },
      "HiddenRewards": [
        {
          "TemplateId": "Token:athena_quest_completed_babayaga",
          "Quantity": 1
        }
      ],
      "Objectives": [
        {
          "BackendName": "quest_s18_transient_BabaYaga_NewBrew_q02_obj0",
          "InlineObjectiveStats": [
            {
              "TagConditions": [
                {
                  "Tag": {
                    "TagName": "Athena.Playlist"
                  },
                  "Type": "EInlineObjectiveStatTagCheckEntryType::Context",
                  "Require": true
                },
                {
                  "Tag": {
                    "TagName": "Homebase.Class"
                  },
                  "Type": "EInlineObjectiveStatTagCheckEntryType::Source",
                  "Require": true
                },
                {
                  "Tag": {
                    "TagName": "Conversation.Entry.VendingMachine.Medical"
                  },
                  "Type": "EInlineObjectiveStatTagCheckEntryType::Target",
                  "Require": true
                }
              ],
              "Condition": "",
              "TemplateIds": [],
              "Type": "EFortQuestObjectiveStatEvent::UsedNPCService",
              "bHasInclusiveTargetTags": true,
              "bHasInclusiveSourceTags": true,
              "bHasInclusiveContextTags": true
            }
          ],
          "ObjectiveStatHandle": {
            "DataTable": null,
            "RowName": null
          },
          "AlternativeStatHandles": [],
          "ItemEvent": "EFortQuestObjectiveItemEvent::Max_None",
          "bHidden": false,
          "bRequirePrimaryMissionCompletion": false,
          "bCanProgressInZone": true,
          "bDisplayDynamicAnnouncementUpdate": false,
          "DynamicStatusUpdateType": "EObjectiveStatusUpdateType::Always",
          "LinkVaultTab": "EFortInventoryFilter::Max_None",
          "LinkToItemManagement": "EFortFrontendInventoryFilter::Max_None",
          "ItemReference": {
            "AssetPathName": "None",
            "SubPathString": ""
          },
          "ItemTemplateIdOverride": "",
          "LinkSquadID": null,
          "LinkSquadIndex": 0,
          "Description": {
            "Namespace": "",
            "Key": "02B36E89459032C6DB9BFC9D45B3EF74",
            "SourceString": "Use any of the services of a Mending Machine"
          },
          "HudShortDescription": {
            "Namespace": "",
            "Key": "6D6DD95A4B401612ADDB398617E18958",
            "SourceString": "Perhaps I have something to learn from the mass market. "
          },
          "HudIcon": {
            "AssetPathName": "None",
            "SubPathString": ""
          },
          "Count": 1,
          "Stage": -1,
          "DynamicStatusUpdatePercentInterval": 1,
          "DynamicUpdateCompletionDelay": 1.0,
          "ScriptedAction": {
            "AssetPathName": "None",
            "SubPathString": ""
          },
          "FrontendScriptedAction": {
            "AssetPathName": "None",
            "SubPathString": ""
          }
        }
      ],
      "QuestsToComplete": [
        {
          "AssetPathName": "/BattlePassS18/Items/QuestItems/PunchCard/Questline/S18_Complete_BabaYaga_NewBrew_q02.S18_Complete_BabaYaga_NewBrew_q02",
          "SubPathString": ""
        }
      ],
      "CompletionText": {
        "Namespace": "quest_s18_transient_BabaYaga_NewBrew_q02",
        "Key": "quest_s18_transient_BabaYaga_NewBrew_q02_CompletionText",
        "SourceString": "Ha! That cute little goat box is on to something!"
      },
      "TransientQuestStage": 2,
      "TransientQuestMaxStage": 5,
      "GrantToProfileType": "athena",
      "DisplayName": {
        "Namespace": "quest_s18_transient_BabaYaga_NewBrew_q02",
        "Key": "quest_s18_transient_BabaYaga_NewBrew_q02_DisplayName",
        "SourceString": "Use any of the services of a Mending Machine"
      },
      "ShortDescription": {
        "Namespace": "quest_s18_transient_BabaYaga_NewBrew_q02",
        "Key": "quest_s18_transient_BabaYaga_NewBrew_q02_ShortDescription",
        "SourceString": "Perhaps I have something to learn from the mass market. "
      },
      "Description": {
        "Namespace": "quest_s18_transient_BabaYaga_NewBrew_q02",
        "Key": "quest_s18_transient_BabaYaga_NewBrew_q02_Description",
        "SourceString": "Use any of the services of a Mending Machine"
      },
      "GameplayTags": [
        "ChallengeCategory.Bars"
      ]
    }
  }
]