[
  {
    "Type": "FortQuestItemDefinition",
    "Name": "quest_s18_transient_headbandk_fortjutsu_q01",
    "Properties": {
      "QuestType": "EFortQuestType::AthenaTransientQuest",
      "TandemCharacterData": {
        "AssetPathName": "/HeadbandAi/HeadbandK/CharacterData/NPCCharacterData_HeadbandK.NPCCharacterData_HeadbandK",
        "SubPathString": ""
      },
      "bIncludedInCategories": false,
      "bIsShared": true,
      "Rewards": [
        {
          "ItemPrimaryAssetId": {
            "PrimaryAssetType": {
              "Name": "Quest"
            },
            "PrimaryAssetName": "quest_s18_transient_headbandk_fortjutsu_q02"
          },
          "Quantity": 1
        }
      ],
      "RewardsTable": {
        "ObjectName": "DataTable ChallengeReward_S18_ShardQuest_C",
        "ObjectPath": "/BattlePassS18/Items/QuestRewards/ChallengeReward_S18_ShardQuest_C.0"
      },
      "HiddenRewards": [
        {
          "TemplateId": "Token:athena_quest_completed_headbandk",
          "Quantity": 1
        }
      ],
      "Objectives": [
        {
          "BackendName": "quest_s18_transient_headbandk_fortjutsu_q01_obj0",
          "InlineObjectiveStats": [
            {
              "TagConditions": [
                {
                  "Tag": {
                    "TagName": "Athena.Quests.S18.Headband.ScoutUFO"
                  },
                  "Type": "EInlineObjectiveStatTagCheckEntryType::Target",
                  "Require": true
                }
              ],
              "Condition": "",
              "TemplateIds": [],
              "Type": "EFortQuestObjectiveStatEvent::ComplexCustom",
              "bHasInclusiveTargetTags": true,
              "bHasInclusiveSourceTags": false,
              "bHasInclusiveContextTags": false
            }
          ],
          "ObjectiveStatHandle": {
            "DataTable": null,
            "RowName": null
          },
          "AlternativeStatHandles": [],
          "ItemEvent": "EFortQuestObjectiveItemEvent::Max_None",
          "bHidden": false,
          "bRequirePrimaryMissionCompletion": false,
          "bCanProgressInZone": true,
          "bDisplayDynamicAnnouncementUpdate": false,
          "DynamicStatusUpdateType": "EObjectiveStatusUpdateType::Always",
          "LinkVaultTab": "EFortInventoryFilter::Max_None",
          "LinkToItemManagement": "EFortFrontendInventoryFilter::Max_None",
          "ItemReference": {
            "AssetPathName": "None",
            "SubPathString": ""
          },
          "ItemTemplateIdOverride": "",
          "LinkSquadID": null,
          "LinkSquadIndex": 0,
          "Description": {
            "Namespace": "",
            "Key": "7D8964794A3035E270CC0988E61BBCD0",
            "SourceString": "Scout a UFO crash site"
          },
          "HudShortDescription": {
            "Namespace": "",
            "Key": "83A2328C4EF79486B158A98E6CBAE5C0",
            "SourceString": "Scout a UFO crash site"
          },
          "HudIcon": {
            "AssetPathName": "None",
            "SubPathString": ""
          },
          "Count": 1,
          "Stage": -1,
          "DynamicStatusUpdatePercentInterval": 25,
          "DynamicUpdateCompletionDelay": 1.0,
          "ScriptedAction": {
            "AssetPathName": "None",
            "SubPathString": ""
          },
          "FrontendScriptedAction": {
            "AssetPathName": "None",
            "SubPathString": ""
          }
        }
      ],
      "QuestsToComplete": [
        {
          "AssetPathName": "/BattlePassS18/Items/QuestItems/PunchCard/Questline/S18_Complete_HeadbandK_FortJutsu_q01.S18_Complete_HeadbandK_FortJutsu_q01",
          "SubPathString": ""
        }
      ],
      "CompletionText": {
        "Namespace": "quest_s18_transient_headbandk_fortjutsu_q01",
        "Key": "quest_s18_transient_headbandk_fortjutsu_q01_CompletionText",
        "SourceString": "Now you can use the terrain to your advantage."
      },
      "TransientQuestStage": 1,
      "TransientQuestMaxStage": 5,
      "GrantToProfileType": "athena",
      "Rarity": "EFortRarity::Common",
      "DisplayName": {
        "Namespace": "quest_s18_transient_headbandk_fortjutsu_q01",
        "Key": "quest_s18_transient_headbandk_fortjutsu_q01_DisplayName",
        "SourceString": "Scout a UFO crash site"
      },
      "ShortDescription": {
        "Namespace": "quest_s18_transient_headbandk_fortjutsu_q01",
        "Key": "quest_s18_transient_headbandk_fortjutsu_q01_ShortDescription",
        "SourceString": "First, a ninja must scout the battlefield."
      },
      "Description": {
        "Namespace": "quest_s18_transient_headbandk_fortjutsu_q01",
        "Key": "quest_s18_transient_headbandk_fortjutsu_q01_Description",
        "SourceString": "Scout a UFO crash site"
      },
      "GameplayTags": [
        "Athena.Quests.S18.Headband.ScoutUFO.01",
        "Athena.Quests.S18.Headband.ScoutUFO.02",
        "Athena.Quests.S18.Headband.ScoutUFO.03",
        "Athena.Quests.S18.Headband.ScoutUFO.04",
        "Athena.Quests.S18.Headband.ScoutUFO.05"
      ]
    }
  }
]