[
  {
    "Type": "FortQuestItemDefinition",
    "Name": "quest_s17_w03_legendary_q4",
    "Properties": {
      "QuestType": "EFortQuestType::AthenaChallengeBundleQuest",
      "QuestSubtype": "EFortQuestSubtype::WeeklyChallenge",
      "TandemCharacterData": {
        "AssetPathName": "/NPCLibrary/NPCs/Faux/Faux/NPCCharacterData_Faux.NPCCharacterData_Faux",
        "SubPathString": ""
      },
      "bIncludedInCategories": false,
      "ObjectiveCompletionCount": 2,
      "Rewards": [
        {
          "ItemPrimaryAssetId": {
            "PrimaryAssetType": {
              "Name": "Quest"
            },
            "PrimaryAssetName": "quest_s17_w03_legendary_q5"
          },
          "Quantity": 1
        }
      ],
      "RewardsTable": {
        "ObjectName": "ChallengeReward_S17_LegendaryXP_Stage4:DataTable",
        "ObjectPath": "/BattlepassS17/Items/QuestRewards/ChallengeReward_S17_LegendaryXP_Stage4.0"
      },
      "HiddenRewards": [
        {
          "TemplateId": "Token:athenabattlepass_s17_w03",
          "Quantity": 1
        }
      ],
      "Objectives": [
        {
          "BackendName": "quest_s17_w03_legendary_q4_obj0",
          "InlineObjectiveStats": [
            {
              "TagConditions": [
                {
                  "Tag": {
                    "TagName": "Athena.Playlist"
                  },
                  "Type": "EInlineObjectiveStatTagCheckEntryType::Context",
                  "Require": true
                },
                {
                  "Tag": {
                    "TagName": "Homebase.Class"
                  },
                  "Type": "EInlineObjectiveStatTagCheckEntryType::Source",
                  "Require": true
                },
                {
                  "Tag": {
                    "TagName": "Athena.Quests.Place.Light.00"
                  },
                  "Type": "EInlineObjectiveStatTagCheckEntryType::Target",
                  "Require": true
                }
              ],
              "Condition": "",
              "TemplateIds": [],
              "Type": "EFortQuestObjectiveStatEvent::Interact",
              "bHasInclusiveTargetTags": true,
              "bHasInclusiveSourceTags": true,
              "bHasInclusiveContextTags": true
            }
          ],
          "ObjectiveStatHandle": {
            "DataTable": null,
            "RowName": null
          },
          "AlternativeStatHandles": [],
          "ItemEvent": "EFortQuestObjectiveItemEvent::Max_None",
          "bHidden": false,
          "bRequirePrimaryMissionCompletion": false,
          "bCanProgressInZone": true,
          "bDisplayDynamicAnnouncementUpdate": false,
          "DynamicStatusUpdateType": "EObjectiveStatusUpdateType::OnComplete",
          "LinkVaultTab": "EFortInventoryFilter::Max_None",
          "LinkToItemManagement": "EFortFrontendInventoryFilter::Max_None",
          "ItemReference": {
            "AssetPathName": "None",
            "SubPathString": ""
          },
          "ItemTemplateIdOverride": "",
          "LinkSquadID": null,
          "LinkSquadIndex": 0,
          "Description": {
            "Namespace": "",
            "Key": "320FE19B481AFFF1928739869E2F4AFE",
            "SourceString": "Place alien light communication device on mountain tops"
          },
          "HudShortDescription": {
            "Namespace": "",
            "Key": "07E464724732E5C27FCA75930CFD0723",
            "SourceString": "Place alien light communication device on mountain tops"
          },
          "HudIcon": {
            "AssetPathName": "None",
            "SubPathString": ""
          },
          "Count": 1,
          "Stage": -1,
          "DynamicStatusUpdatePercentInterval": 25,
          "DynamicUpdateCompletionDelay": 1.0,
          "ScriptedAction": {
            "AssetPathName": "None",
            "SubPathString": ""
          },
          "FrontendScriptedAction": {
            "AssetPathName": "None",
            "SubPathString": ""
          }
        },
        {
          "BackendName": "quest_s17_w03_legendary_q4_obj1",
          "InlineObjectiveStats": [
            {
              "TagConditions": [
                {
                  "Tag": {
                    "TagName": "Athena.Playlist"
                  },
                  "Type": "EInlineObjectiveStatTagCheckEntryType::Context",
                  "Require": true
                },
                {
                  "Tag": {
                    "TagName": "Homebase.Class"
                  },
                  "Type": "EInlineObjectiveStatTagCheckEntryType::Source",
                  "Require": true
                },
                {
                  "Tag": {
                    "TagName": "Athena.Quests.Place.Light.01"
                  },
                  "Type": "EInlineObjectiveStatTagCheckEntryType::Target",
                  "Require": true
                }
              ],
              "Condition": "",
              "TemplateIds": [],
              "Type": "EFortQuestObjectiveStatEvent::Interact",
              "bHasInclusiveTargetTags": true,
              "bHasInclusiveSourceTags": true,
              "bHasInclusiveContextTags": true
            }
          ],
          "ObjectiveStatHandle": {
            "DataTable": null,
            "RowName": null
          },
          "AlternativeStatHandles": [],
          "ItemEvent": "EFortQuestObjectiveItemEvent::Max_None",
          "bHidden": false,
          "bRequirePrimaryMissionCompletion": false,
          "bCanProgressInZone": true,
          "bDisplayDynamicAnnouncementUpdate": false,
          "DynamicStatusUpdateType": "EObjectiveStatusUpdateType::OnComplete",
          "LinkVaultTab": "EFortInventoryFilter::Max_None",
          "LinkToItemManagement": "EFortFrontendInventoryFilter::Max_None",
          "ItemReference": {
            "AssetPathName": "None",
            "SubPathString": ""
          },
          "ItemTemplateIdOverride": "",
          "LinkSquadID": null,
          "LinkSquadIndex": 0,
          "Description": {
            "Namespace": "",
            "Key": "BC638B6049D2663E1A3C68A681131BEC",
            "SourceString": "Place alien light communication device on mountain tops"
          },
          "HudShortDescription": {
            "Namespace": "",
            "Key": "17D4D80444B9FB69F593C6B1BAD76F54",
            "SourceString": "Place alien light communication device on mountain tops"
          },
          "HudIcon": {
            "AssetPathName": "None",
            "SubPathString": ""
          },
          "Count": 1,
          "Stage": -1,
          "DynamicStatusUpdatePercentInterval": 25,
          "DynamicUpdateCompletionDelay": 1.0,
          "ScriptedAction": {
            "AssetPathName": "None",
            "SubPathString": ""
          },
          "FrontendScriptedAction": {
            "AssetPathName": "None",
            "SubPathString": ""
          }
        },
        {
          "BackendName": "quest_s17_w03_legendary_q4_obj2",
          "InlineObjectiveStats": [
            {
              "TagConditions": [
                {
                  "Tag": {
                    "TagName": "Athena.Playlist"
                  },
                  "Type": "EInlineObjectiveStatTagCheckEntryType::Context",
                  "Require": true
                },
                {
                  "Tag": {
                    "TagName": "Homebase.Class"
                  },
                  "Type": "EInlineObjectiveStatTagCheckEntryType::Source",
                  "Require": true
                },
                {
                  "Tag": {
                    "TagName": "Athena.Quests.Place.Light.02"
                  },
                  "Type": "EInlineObjectiveStatTagCheckEntryType::Target",
                  "Require": true
                }
              ],
              "Condition": "",
              "TemplateIds": [],
              "Type": "EFortQuestObjectiveStatEvent::Interact",
              "bHasInclusiveTargetTags": true,
              "bHasInclusiveSourceTags": true,
              "bHasInclusiveContextTags": true
            }
          ],
          "ObjectiveStatHandle": {
            "DataTable": null,
            "RowName": null
          },
          "AlternativeStatHandles": [],
          "ItemEvent": "EFortQuestObjectiveItemEvent::Max_None",
          "bHidden": false,
          "bRequirePrimaryMissionCompletion": false,
          "bCanProgressInZone": true,
          "bDisplayDynamicAnnouncementUpdate": false,
          "DynamicStatusUpdateType": "EObjectiveStatusUpdateType::OnComplete",
          "LinkVaultTab": "EFortInventoryFilter::Max_None",
          "LinkToItemManagement": "EFortFrontendInventoryFilter::Max_None",
          "ItemReference": {
            "AssetPathName": "None",
            "SubPathString": ""
          },
          "ItemTemplateIdOverride": "",
          "LinkSquadID": null,
          "LinkSquadIndex": 0,
          "Description": {
            "Namespace": "",
            "Key": "54EE9EB84F58C6E7A02AE88B3E0AD9CF",
            "SourceString": "Place alien light communication device on mountain tops"
          },
          "HudShortDescription": {
            "Namespace": "",
            "Key": "85F7E03C428E525427F59FBA5AC81966",
            "SourceString": "Place alien light communication device on mountain tops"
          },
          "HudIcon": {
            "AssetPathName": "None",
            "SubPathString": ""
          },
          "Count": 1,
          "Stage": -1,
          "DynamicStatusUpdatePercentInterval": 25,
          "DynamicUpdateCompletionDelay": 1.0,
          "ScriptedAction": {
            "AssetPathName": "None",
            "SubPathString": ""
          },
          "FrontendScriptedAction": {
            "AssetPathName": "None",
            "SubPathString": ""
          }
        },
        {
          "BackendName": "quest_s17_w03_legendary_q4_obj3",
          "InlineObjectiveStats": [
            {
              "TagConditions": [
                {
                  "Tag": {
                    "TagName": "Athena.Playlist"
                  },
                  "Type": "EInlineObjectiveStatTagCheckEntryType::Context",
                  "Require": true
                },
                {
                  "Tag": {
                    "TagName": "Homebase.Class"
                  },
                  "Type": "EInlineObjectiveStatTagCheckEntryType::Source",
                  "Require": true
                },
                {
                  "Tag": {
                    "TagName": "Athena.Quests.Place.Light.03"
                  },
                  "Type": "EInlineObjectiveStatTagCheckEntryType::Target",
                  "Require": true
                }
              ],
              "Condition": "",
              "TemplateIds": [],
              "Type": "EFortQuestObjectiveStatEvent::Interact",
              "bHasInclusiveTargetTags": true,
              "bHasInclusiveSourceTags": true,
              "bHasInclusiveContextTags": true
            }
          ],
          "ObjectiveStatHandle": {
            "DataTable": null,
            "RowName": null
          },
          "AlternativeStatHandles": [],
          "ItemEvent": "EFortQuestObjectiveItemEvent::Max_None",
          "bHidden": false,
          "bRequirePrimaryMissionCompletion": false,
          "bCanProgressInZone": true,
          "bDisplayDynamicAnnouncementUpdate": false,
          "DynamicStatusUpdateType": "EObjectiveStatusUpdateType::OnComplete",
          "LinkVaultTab": "EFortInventoryFilter::Max_None",
          "LinkToItemManagement": "EFortFrontendInventoryFilter::Max_None",
          "ItemReference": {
            "AssetPathName": "None",
            "SubPathString": ""
          },
          "ItemTemplateIdOverride": "",
          "LinkSquadID": null,
          "LinkSquadIndex": 0,
          "Description": {
            "Namespace": "",
            "Key": "663B68A34973DE381ADAAABBA97D6FD2",
            "SourceString": "Place alien light communication device on mountain tops"
          },
          "HudShortDescription": {
            "Namespace": "",
            "Key": "582E3B28466D42A06F5642A0D95FB1FF",
            "SourceString": "Place alien light communication device on mountain tops"
          },
          "HudIcon": {
            "AssetPathName": "None",
            "SubPathString": ""
          },
          "Count": 1,
          "Stage": -1,
          "DynamicStatusUpdatePercentInterval": 25,
          "DynamicUpdateCompletionDelay": 1.0,
          "ScriptedAction": {
            "AssetPathName": "None",
            "SubPathString": ""
          },
          "FrontendScriptedAction": {
            "AssetPathName": "None",
            "SubPathString": ""
          }
        }
      ],
      "CompletionText": {
        "Namespace": "quest_s17_w03_legendary_q4",
        "Key": "quest_s17_w03_legendary_q4_CompletionText",
        "SourceString": "That'll show 'em. Now... make sure you don't move those beacons?"
      },
      "GrantToProfileType": "athena",
      "Rarity": "EFortRarity::Legendary",
      "DisplayName": {
        "Namespace": "quest_s17_w03_legendary_q4",
        "Key": "quest_s17_w03_legendary_q4_DisplayName",
        "SourceString": "Place alien light communication device on mountain tops"
      },
      "ShortDescription": {
        "Namespace": "quest_s17_w03_legendary_q4",
        "Key": "quest_s17_w03_legendary_q4_ShortDescription",
        "SourceString": "Between you an me - I know how to disrupt the mothership's communications."
      },
      "Description": {
        "Namespace": "quest_s17_w03_legendary_q4",
        "Key": "quest_s17_w03_legendary_q4_Description",
        "SourceString": "Place alien light communication device on mountain tops"
      }
    }
  }
]