[
  {
    "Type": "SoundCue",
    "Name": "NPC_Evil_Boss_Final_Impact_Cue",
    "Properties": {
      "FirstNode": {
        "ObjectName": "NPC_Evil_Boss_Final_Impact_Cue:SoundNodeWavePlayer_0:SoundNodeWavePlayer",
        "ObjectPath": "/NPCLibrary/Audio/TinyBalloon/NPC_Evil_Boss_Final_Impact_Cue.1"
      },
      "VolumeMultiplier": 1.2,
      "SoundClassObject": {
        "ObjectName": "Fort_WeaponMelee_PSM:SoundClass",
        "ObjectPath": "/Game/Sounds/FortSoundClassesAndModes/Fort_WeaponMelee_PSM.0"
      },
      "ConcurrencySet": [
        {
          "ObjectName": "Evil_Boss_Con:SoundConcurrency",
          "ObjectPath": "/NPCLibrary/Audio/TinyBalloon/Evil_Boss_Con.0"
        }
      ],
      "ConcurrencyOverrides": {
        "MaxCount": 1,
        "bLimitToOwner": true
      },
      "Duration": 1.8647292,
      "MaxDistance": 3500.0,
      "Priority": 2.0,
      "AttenuationSettings": {
        "ObjectName": "Fort_Explosion_Close_Att:SoundAttenuation",
        "ObjectPath": "/Game/Sounds/Attenuation/Fort_Explosion_Close_Att.0"
      }
    }
  },
  {
    "Type": "SoundNodeWavePlayer",
    "Name": "SoundNodeWavePlayer_0",
    "Properties": {
      "SoundWaveAssetPtr": {
        "AssetPathName": "/NPCLibrary/Audio/TinyBalloon/Evil_Boss_Final_Impact_01.Evil_Boss_Final_Impact_01",
        "SubPathString": ""
      }
    }
  }
]