[
  {
    "Type": "FortQuestItemDefinition",
    "Name": "Quest_S16_W12_Epic_Q02",
    "Properties": {
      "QuestType": "EFortQuestType::AthenaChallengeBundleQuest",
      "QuestSubtype": "EFortQuestSubtype::WeeklyChallenge",
      "TandemCharacterData": {
        "AssetPathName": "/NPCLibrary/NPCs/Deadfire/Deadfire/NPCCharacterData_Deadfire.NPCCharacterData_Deadfire",
        "SubPathString": ""
      },
      "bIncludedInCategories": false,
      "Threshold": 1,
      "Rewards": [
        {
          "ItemPrimaryAssetId": {
            "PrimaryAssetType": {
              "Name": "Quest"
            },
            "PrimaryAssetName": "Quest_S16_W12_Epic_Q03"
          },
          "Quantity": 1
        }
      ],
      "RewardsTable": {
        "ObjectName": "ChallengeReward_S16_WeeklyXP:DataTable",
        "ObjectPath": "/BattlepassS16/Items/QuestRewards/ChallengeReward_S16_WeeklyXP.0"
      },
      "HiddenRewards": [
        {
          "TemplateId": "Token:athenabattlepass_s16_w12",
          "Quantity": 1
        },
        {
          "TemplateId": "Token:athenabattlepass_weeklychallenge_token",
          "Quantity": 1
        }
      ],
      "Objectives": [
        {
          "BackendName": "Quest_S16_W12_Epic_Q02_obj0",
          "InlineObjectiveStats": [
            {
              "TagConditions": [
                {
                  "Tag": {
                    "TagName": "Athena.Playlist"
                  },
                  "Type": "EInlineObjectiveStatTagCheckEntryType::Context",
                  "Require": true
                },
                {
                  "Tag": {
                    "TagName": "Athena.GameOn"
                  },
                  "Type": "EInlineObjectiveStatTagCheckEntryType::Context",
                  "Require": true
                },
                {
                  "Tag": {
                    "TagName": "Homebase.Class"
                  },
                  "Type": "EInlineObjectiveStatTagCheckEntryType::Source",
                  "Require": true
                },
                {
                  "Tag": {
                    "TagName": "Item.Weapon.Ranged.Pistol"
                  },
                  "Type": "EInlineObjectiveStatTagCheckEntryType::Source",
                  "Require": true
                }
              ],
              "Condition": "",
              "TemplateIds": [],
              "Type": "EFortQuestObjectiveStatEvent::AthenaCraft",
              "bHasInclusiveTargetTags": false,
              "bHasInclusiveSourceTags": true,
              "bHasInclusiveContextTags": true
            }
          ],
          "ObjectiveStatHandle": {
            "DataTable": null,
            "RowName": null
          },
          "AlternativeStatHandles": [],
          "ItemEvent": "EFortQuestObjectiveItemEvent::Max_None",
          "bHidden": false,
          "bRequirePrimaryMissionCompletion": false,
          "bCanProgressInZone": true,
          "bDisplayDynamicAnnouncementUpdate": false,
          "DynamicStatusUpdateType": "EObjectiveStatusUpdateType::Always",
          "LinkVaultTab": "EFortInventoryFilter::Max_None",
          "LinkToItemManagement": "EFortFrontendInventoryFilter::Max_None",
          "ItemReference": {
            "AssetPathName": "None",
            "SubPathString": ""
          },
          "ItemTemplateIdOverride": "",
          "LinkSquadID": null,
          "LinkSquadIndex": 0,
          "Description": {
            "Namespace": "",
            "Key": "729CF99C408E3B16C4A96C861FBA0AE6",
            "SourceString": "Craft pistols"
          },
          "HudShortDescription": {
            "Namespace": "",
            "Key": "B5E0CDE349F96A2BDF60209417049EB1",
            "SourceString": "Time to get centered, building pistols calms the soul."
          },
          "HudIcon": {
            "AssetPathName": "None",
            "SubPathString": ""
          },
          "Count": 3,
          "Stage": -1,
          "DynamicStatusUpdatePercentInterval": 20,
          "DynamicUpdateCompletionDelay": 1.0,
          "ScriptedAction": {
            "AssetPathName": "None",
            "SubPathString": ""
          },
          "FrontendScriptedAction": {
            "AssetPathName": "None",
            "SubPathString": ""
          }
        }
      ],
      "CompletionText": {
        "Namespace": "Quest_S16_W12_Epic_Q02",
        "Key": "Quest_S16_W12_Epic_Q02_CompletionText",
        "SourceString": "Nothing like some smoooooth action."
      },
      "GrantToProfileType": "athena",
      "Rarity": "EFortRarity::Epic",
      "DisplayName": {
        "Namespace": "Quest_S16_W12_Epic_Q02",
        "Key": "Quest_S16_W12_Epic_Q02_DisplayName",
        "SourceString": "Craft pistols"
      },
      "ShortDescription": {
        "Namespace": "Quest_S16_W12_Epic_Q02",
        "Key": "Quest_S16_W12_Epic_Q02_ShortDescription",
        "SourceString": "Time to get centered, building pistols calms the soul."
      },
      "Description": {
        "Namespace": "Quest_S16_W12_Epic_Q02",
        "Key": "Quest_S16_W12_Epic_Q02_Description",
        "SourceString": "Craft pistols"
      },
      "GameplayTags": [
        "ChallengeCategory.XP"
      ]
    }
  }
]