[
  {
    "Type": "AnimMontage",
    "Name": "GoopGrenade_Cook_Outro"
  },
  {
    "Type": "AnimNotify_PlaySound",
    "Name": "AnimNotify_PlaySound_0",
    "Outer": "GoopGrenade_Cook_Outro",
    "Properties": {
      "Sound": {
        "ObjectName": "Goop_Throw_Cue:SoundCue",
        "ObjectPath": "/MotherGameplay/Items/Goop/Audio/Goop_Throw_Cue.0"
      },
      "bFollow": true
    }
  },
  {
    "Type": "AnimNotifyState_AttachAsset_C",
    "Name": "AnimNotifyState_AttachAsset_C_0",
    "Outer": "GoopGrenade_Cook_Outro",
    "Template": "Default__AnimNotifyState_AttachAsset_C",
    "Properties": {
      "Attachment": {
        "SocketName": "RightHand",
        "StaticMeshAsset": {
          "ObjectName": "Goop:StaticMesh",
          "ObjectPath": "/MotherGameplay/Items/Goop/Assets/Meshes/Goop.1"
        },
        "bIsCurrentWeaponSubstitute": true
      }
    }
  },
  {
    "Type": "AnimNotifyState_HolsterWeapon_C",
    "Name": "AnimNotifyState_HolsterWeapon_C_0",
    "Outer": "GoopGrenade_Cook_Outro",
    "Template": "Default__AnimNotifyState_HolsterWeapon_C"
  },
  {
    "Type": "FortAnimNotify_TriggerGameplayAbility",
    "Name": "FortAnimNotify_TriggerGameplayAbility_0",
    "Outer": "GoopGrenade_Cook_Outro"
  }
]