[
  {
    "Type": "FortAthenaLivingWorldEventData",
    "Name": "LagerEventData_IO_Entourage",
    "Properties": {
      "ProviderFiltersTagQuery": {
        "TagDictionary": [
          {
            "TagName": "Athena.AI.SpawnLocation.IO.Entourage.01"
          }
        ],
        "QueryTokenStream": [
          0,
          1,
          1,
          1,
          0
        ],
        "AutoDescription": " ANY( Athena.AI.SpawnLocation.IO.Entourage.01 )"
      },
      "ActorDescriptions": [
        {
          "ActorClass": {
            "AssetPathName": "None",
            "SubPathString": ""
          },
          "SpawnerData": {
            "AssetPathName": "None",
            "SubPathString": ""
          },
          "SpawnerDataTagQuery": {
            "TokenStreamVersion": 0,
            "TagDictionary": [
              {
                "TagName": "AISpawnerData.Type.IO.FieldTeam"
              },
              {
                "TagName": "AISpawnerData.Type.IO.Grunt"
              }
            ],
            "QueryTokenStream": [
              0,
              1,
              1,
              2,
              0,
              1
            ],
            "UserDescription": "",
            "AutoDescription": " ANY( AISpawnerData.Type.IO.FieldTeam, AISpawnerData.Type.IO.Grunt )"
          },
          "bUseProviderTagOverrides": false,
          "ProviderFiltersTagQueryOverride": {
            "TokenStreamVersion": 0,
            "TagDictionary": [],
            "QueryTokenStream": [],
            "UserDescription": "",
            "AutoDescription": ""
          },
          "bSpawnAroundDefaultPoint": false,
          "SpawnAroundEnvironmentQuery": null,
          "ActorDensityValue": {
            "Value": 1.0,
            "Curve": {
              "CurveTable": null,
              "RowName": null
            },
            "RegistryType": {
              "Name": null
            }
          },
          "DensityComputationRangeOverride": {
            "Value": -1.0,
            "Curve": {
              "CurveTable": null,
              "RowName": null
            },
            "RegistryType": {
              "Name": null
            }
          },
          "TagDensityRegistrations": []
        }
      ]
    }
  }
]