[
  {
    "Type": "SoundWave",
    "Name": "OuterTowerBoss_2021_Idle_030",
    "Properties": {
      "NumChannels": 2,
      "SampleRate": 48000,
      "Duration": 4.213375,
      "TotalSamples": 202242.0
    },
    "CompressedFormatData": null,
    "RawData": null,
    "CompressedDataGuid": "4A090EEB-4FA40F54-698B8294-E2786978",
    "RunningPlatformData": {
      "NumChunks": 2,
      "AudioFormat": "OGG",
      "Chunks": [
        {
          "DataSize": 6144,
          "AudioDataSize": 6144,
          "BulkData": {
            "BulkDataFlag": "BULKDATA_ForceInlinePayload",
            "ElementCount": 6144,
            "SizeOnDisk": 6144,
            "OffsetInFile": "0x1E3B"
          }
        },
        {
          "DataSize": 34946,
          "AudioDataSize": 34946,
          "BulkData": {
            "BulkDataFlag": "BULKDATA_PayloadInSeperateFile",
            "ElementCount": 34946,
            "SizeOnDisk": 34946,
            "OffsetInFile": "0x0"
          }
        }
      ]
    }
  }
]